llqqntinstaller/__main__.py
llqqntinstaller/util.py
llqqntinstaller_py-0.2.2.dist-info/LICENSE
llqqntinstaller_py-0.2.2.dist-info/METADATA
llqqntinstaller_py-0.2.2.dist-info/WHEEL
llqqntinstaller_py-0.2.2.dist-info/RECORD
